beets_usertag-1.0.1.dist-info/licenses/LICENSE
beetsplug/__init__.py
beetsplug/usertag.py
beets_usertag-1.0.1.dist-info/METADATA
beets_usertag-1.0.1.dist-info/WHEEL
beets_usertag-1.0.1.dist-info/top_level.txt
beets_usertag-1.0.1.dist-info/RECORD
