Metadata-Version: 2.4
Name: beets-usertag
Version: 1.0.1
Summary: beets plugin to support user defined keyword tags
Author-email: Ingo Fruend <github@ingofruend.net>, Edgars Supe <github@epus.lv>
License-Expression: MIT
Project-URL: Homepage, https://github.com/edgars-supe/beets-usertag
Keywords: beets
Requires-Python: >=3.7
License-File: LICENSE
Requires-Dist: beets>=1.5.0
Provides-Extra: dev
Requires-Dist: responses; extra == "dev"
Requires-Dist: pytest; extra == "dev"
Dynamic: license-file
